molda/ATCVectorizer.py
molda/Gref94Vectorizer.py
molda/LTUVectorizer.py
molda/ObservedExpected.py
molda/Tficf.py
molda/TtestVectorizer.py
molda/__init__.py
molda/errors.py
molda-0.1.2.dist-info/LICENSE
molda-0.1.2.dist-info/METADATA
molda-0.1.2.dist-info/WHEEL
molda-0.1.2.dist-info/top_level.txt
molda-0.1.2.dist-info/RECORD
