Metadata-Version: 2.1
Name: molda
Version: 0.1.2
Summary: Molda is a sci-kit learn inspired Python library for text vectorization of corpora. It is adapted to work in pipelines and numpy arrays.
Home-page: https://github.com/SigmoidAI/molda
Download-URL: https://github.com/ScienceKot/kydavra/archive/v1.0.tar.gz
Author: SigmoidAI - Stojoc Vladimir, Smocvin Denis, Butucea Andrei, Sclifos Tudor
Author-email: vladimir.stojoc@gmail.com
License: MIT
Keywords: ml,machine learning,natural language processing,python
Classifier: Development Status :: 3 - Alpha
Classifier: Framework :: Jupyter
Classifier: Intended Audience :: Science/Research
Classifier: Topic :: Scientific/Engineering :: Artificial Intelligence
Classifier: Topic :: Scientific/Engineering :: Mathematics
Classifier: Topic :: Software Development :: Libraries :: Python Modules
Classifier: Topic :: Software Development :: Build Tools
Classifier: License :: OSI Approved :: MIT License
Classifier: Programming Language :: Python :: 3
Classifier: Programming Language :: Python :: 3.4
Classifier: Programming Language :: Python :: 3.5
Classifier: Programming Language :: Python :: 3.6
Classifier: Programming Language :: Python :: 3.7
Classifier: Programming Language :: Python :: 3.8
Classifier: Programming Language :: Python :: 3.9
Classifier: Programming Language :: Python :: 3.10
Classifier: Programming Language :: Python :: 3.11
License-File: LICENSE
Requires-Dist: numpy
Requires-Dist: scikit-learn
Requires-Dist: scipy
